[{"created_at": "2014-05-20T00:11:41", "id": 468544552240812032, "sentiment": 0.0, "text": "#gohabsgo @CanadiensMTL http://t.co/qsgPz3AOOC", "username": "stephenharper"}, {"created_at": "2014-05-20T00:26:40", "id": 468548324178407424, "sentiment": 0.04999999999999999, "text": "What's better than watching the game with the coach? Also with @Min_Lebel! #gohabsgo @CanadiensMTL http://t.co/Zfxd9Lgiuw", "username": "stephenharper"}, {"created_at": "2014-05-20T00:27:11", "id": 468548454147321856, "sentiment": 0.0, "text": "In the release of the Tantauco Park book with Oscar and Patricio Rodrigo. http://t.co/ZzVSoX3Lqe http://t.co/PnNmZ2mSh6", "username": "sebastianpinera"}, {"created_at": "2014-05-20T04:21:56", "id": 468607533330874369, "sentiment": 0.13636363636363635, "text": "[Adm-02] P-Noy administers the oath taking of thirty-seven new generals and flag officers of the AFP in Malaca\u00f1ang. http://t.co/Uuucg4fxoI", "username": "noynoyaquino"}, {"created_at": "2014-05-20T05:31:51", "id": 468625128180690944, "sentiment": 0.4, "text": " @robertszile thank you for this morning's duel @ 900sekundes - qualitative discussion on the important work of the EP and EN 'interests #EPvelesanas", "username": "VDombrovskis"}, {"created_at": "2014-05-20T06:04:38", "id": 468633378020155392, "sentiment": 0.2, "text": "I'll be on Today @BBCRadio4 at 810am, talking about why voting Conservative on Thursday really matters and our #LongTermEconomicPlan.", "username": "David_Cameron"}, {"created_at": "2014-05-20T07:27:51", "id": 468654317012918272, "sentiment": 0.0, "text": "http://t.co/Hdo3SMPzS6", "username": "noynoyaquino"}, {"created_at": "2014-05-20T07:59:39", "id": 468662322957787136, "sentiment": 0.0, "text": "RT @NZNationalParty: We\u2019ve committed $26.5 million over 4 years to protect our kauri forests from dieback disease. http://t.co/rgmv0twEeZ h\u2026", "username": "RtHon_JohnKey"}, {"created_at": "2014-05-20T08:40:41", "id": 468672649632415744, "sentiment": 0.037500000000000006, "text": "Russia prefers not to politicise trade and economic relations with other countries http://t.co/cp8j5U2H2U", "username": "MedvedevRussiaE"}, {"created_at": "2014-05-20T09:34:07", "id": 468686093047832576, "sentiment": 0.09999999999999999, "text": "The pain is common to all people. Those who can mourn at the same time are the ones who can feel the sadness of their brother like their own sadness.", "username": "RT_Erdogan"}, {"created_at": "2014-05-20T09:40:27", "id": 468687687692869633, "sentiment": 0.7000000000000001, "text": "Within 77 million, how happy is the joy of my love, and the sadness of those who are upset is my sadness.", "username": "RT_Erdogan"}, {"created_at": "2014-05-20T09:42:38", "id": 468688238623076353, "sentiment": 0.0, "text": "As the prime minister of this country, I expressly state that even a sheep grazing on the edge of the Tigris is under my responsibility.", "username": "RT_Erdogan"}, {"created_at": "2014-05-20T09:51:33", "id": 468690481455857664, "sentiment": 0.0, "text": "Participating today at @gavialliance mtg. @EU_Commission pledges contribution of \u20ac25 Million per year btw 2014-2020 http://t.co/COAiLFc7qc", "username": "JMDBarroso"}, {"created_at": "2014-05-20T11:24:58", "id": 468713992559800320, "sentiment": 0.3333333333333333, "text": "Pleased to support @loveurlocalmkt. I visited the vibrant @witneymarket at the weekend. #LYLM2014 http://t.co/zO9UMSgdYj", "username": "David_Cameron"}, {"created_at": "2014-05-20T12:41:03", "id": 468733137577459714, "sentiment": 0.0, "text": "Today we opened the Arab Media Forum in its 13th year. An Arab media platform for enriching dialogue, presenting ideas and drawing attention to the reality and future of the media.", "username": "HHShkMohd"}, {"created_at": "2014-05-20T12:41:55", "id": 468733354662060032, "sentiment": 0.18333333333333335, "text": "The formulation, circulation and dissemination of information has seen a revolution in form over the past years. But the real content and the honest word remains what we are always looking for", "username": "HHShkMohd"}, {"created_at": "2014-05-20T12:43:22", "id": 468733722255032320, "sentiment": 0.07777777777777778, "text": "Our definition of the media has changed. Our view of the real influencers has changed, and our social and political reality has changed. We must understand and understand these variables.", "username": "HHShkMohd"}, {"created_at": "2014-05-20T12:44:42", "id": 468734056100679680, "sentiment": 0.34375, "text": "The Arab Media Forum is the largest gathering of Arab media. I hope that the conference environment will be stimulating, rich and inspiring to shape a better future for our Arab media.", "username": "HHShkMohd"}, {"created_at": "2014-05-20T13:08:54", "id": 468740147140644864, "sentiment": 0.0, "text": "Read my speech at the @gavialliance meeting now online at http://t.co/NlFbMNe0Qv", "username": "JMDBarroso"}, {"created_at": "2014-05-20T13:12:09", "id": 468740965088624640, "sentiment": 0.0, "text": "In tribute to St\u00e9phane Hessel, yesterday inauguration of the St\u00e9phane Hessel square at @ ULBruxelles http://t.co/HrG1r6GUlW", "username": "eliodirupo"}, {"created_at": "2014-05-20T13:51:51", "id": 468750954897342464, "sentiment": 0.0, "text": "Pasta al dente! At the inauguration of the Ixina store in Quaregnon - Inhuldiging v / e Ixina-vestiging in Quaregnon http://t.co/pcaVitLavZ", "username": "eliodirupo"}, {"created_at": "2014-05-20T13:54:47", "id": 468751692604129280, "sentiment": 0.0, "text": "My thanks to the US Coastguard, which has resumed its search for our missing yachtsmen. @USCG", "username": "David_Cameron"}, {"created_at": "2014-05-20T14:31:47", "id": 468761006660124672, "sentiment": 0.10876623376623376, "text": "RT @PSofficiel: @JohanneMontay @lavenirpol Program proximity between right-wing parties is not new http://t.co/R90zGAK...", "username": "eliodirupo"}, {"created_at": "2014-05-20T14:32:32", "id": 468761192610418688, "sentiment": 0.0, "text": "RT @lavenirpol: Marcourt (PS) on the One (Regiopoly): The MR has a program \"N-VA compatible\" # BE2505", "username": "eliodirupo"}, {"created_at": "2014-05-20T15:05:44", "id": 468769548494454785, "sentiment": -0.22361111111111115, "text": "Our freedoms weren't just handed down, they were hard won. Humbling to meet some of our D-Day veterans 70 years on. http://t.co/ChRkZEIDKk", "username": "David_Cameron"}, {"created_at": "2014-05-20T16:04:37", "id": 468784369558384643, "sentiment": 0.2, "text": "Don't miss your chance to vote for real change in Europe and an in-out referendum - vote Conservative on Thursday. http://t.co/H5pwfn9ULg", "username": "David_Cameron"}, {"created_at": "2014-05-20T16:13:15", "id": 468786538705604609, "sentiment": 0.0, "text": "Door-to-door in Courcelles with @PaulMagnette @PSofficiel #PlusFortsEnsemble http://t.co/8c8oHmsRx7", "username": "eliodirupo"}, {"created_at": "2014-05-20T16:30:18", "id": 468790831688589314, "sentiment": 0.13636363636363635, "text": "RT @GuatemalaGob: Live - Presentation of the \"National Policy for the Prevention of Violence and Crime 2014 - 2034\" | http://t.co/YEpG...", "username": "ottoperezmolina"}, {"created_at": "2014-05-20T18:24:57", "id": 468819683899346944, "sentiment": 0.0, "text": "With the family of the International Academy of Oman in celebration of the 10th anniversary of the founding of the school # Education ... http://t.co/qjdP2FqOC3", "username": "QueenRania"}, {"created_at": "2014-05-20T18:47:21", "id": 468825319852765184, "sentiment": 0.0, "text": "Mine tanker er med de mennesker i Balkan, som st\u00e5r overfor de verste oversv\u00f8mmelser i over 100 \u00e5r", "username": "jensstoltenberg"}, {"created_at": "2014-05-20T19:16:56", "id": 468832767057620992, "sentiment": 0.0, "text": "Prime Minister Antonis Samaras speech on Greece's Development Plan http://t.co/z6UlMklewm", "username": "PrimeministerGR"}, {"created_at": "2014-05-20T20:29:14", "id": 468850961256296448, "sentiment": 0.0, "text": "Prime Minister Antonis Samaras speech on Greece's Development Plan https://t.co/bmkACdADTd", "username": "PrimeministerGR"}, {"created_at": "2014-05-20T21:03:14", "id": 468859515296026624, "sentiment": 0.0, "text": "Sen Andreychuk & former Ontario Premier Mike Harris will lead our election observation mission to #Ukraine: http://t.co/5SPLcTtuhJ #cdnpoli", "username": "stephenharper"}, {"created_at": "2014-05-20T21:25:44", "id": 468865178785026048, "sentiment": 0.0, "text": "@SloanShuler but I do follow you.", "username": "AmamaMbabazi"}, {"created_at": "2014-05-20T21:38:13", "id": 468868319664406530, "sentiment": 0.4166666666666667, "text": "@bahiigav I am fine. Thank you for asking. And how are you?", "username": "AmamaMbabazi"}, {"created_at": "2014-05-20T21:43:07", "id": 468869553641259010, "sentiment": 0.0, "text": "@wejuli yes I agree, but how does an account get verified?", "username": "AmamaMbabazi"}, {"created_at": "2014-05-20T22:32:33", "id": 468881994018226176, "sentiment": 0.13636363636363635, "text": "Our Tourism Growth Partnership will invest in six projects to grow the tourism sector in New Zealand. http://t.co/CI5DBMf3BC", "username": "RtHon_JohnKey"}, {"created_at": "2014-05-20T22:34:19", "id": 468882437381304320, "sentiment": 0.16, "text": "The National High Electoral Commission announced that the date of the parliamentary elections will be on June 25. We congratulate the Commission ... http://t.co/XsG9c04H5O", "username": "MustafaAG"}, {"created_at": "2014-05-21T00:31:26", "id": 468911911762165760, "sentiment": 0.16818181818181818, "text": "[Adm-02] View the live stream of the 23rd World Economic Forum on East Asia on this link: http://t.co/WYTfliQ23v http://t.co/LmbNAHEG9W", "username": "noynoyaquino"}, {"created_at": "2014-05-21T01:01:45", "id": 468919542367150080, "sentiment": 0.31666666666666665, "text": "RT @NZNationalParty: We're making sure children & families are among the first to benefit from economic growth. http://t.co/cbGFAaxTPN http\u2026", "username": "RtHon_JohnKey"}, {"created_at": "2014-05-21T02:58:40", "id": 468948966521184256, "sentiment": 0.0, "text": "Wellington reminded everyone that it is a world class film destination at NZ's biggest tourism conference, TRENZ. http://t.co/gdmXTUdd4L", "username": "RtHon_JohnKey"}, {"created_at": "2014-05-21T03:24:37", "id": 468955496826023936, "sentiment": -0.4, "text": "Today in \"De Frente con el Presidente\", we will talk about captures and dismantling of criminal structures. http://t.co/DI1WCmqi7J", "username": "ottoperezmolina"}, {"created_at": "2014-05-21T03:57:45", "id": 468963831772102656, "sentiment": 0.5, "text": "Came across these youngsters on my way into the House. Hope they enjoyed their school trip to Parliament. http://t.co/aW9uzrx4Sc", "username": "RtHon_JohnKey"}, {"created_at": "2014-05-21T04:15:38", "id": 468968332537126913, "sentiment": 0.0, "text": "Guatemala launches preventive violence policy for 20 years. #PrevenirEsVivir http://t.co/9fMRDf5R2U | http://t.co/ZBsJrAVfvb", "username": "ottoperezmolina"}, {"created_at": "2014-05-21T06:49:15", "id": 469006991109914624, "sentiment": 0.25, "text": "A chat with @TelegraphLondon on my Global Partnership for Education @GPforEducation work & more - JG.         http://t.co/b4V04MU5yB", "username": "JuliaGillard"}, {"created_at": "2014-05-21T07:58:30", "id": 469024421043507200, "sentiment": 0.0, "text": "'My priorities: job creation (youth guarantee, integration contract), +120 euros net / month for workers, indexing' @Soirmag", "username": "eliodirupo"}, {"created_at": "2014-05-21T07:58:45", "id": 469024481328242688, "sentiment": 0.0, "text": "'We want a wealth tax & a tax on financial transactions to finance a salary increase' @Soirmag", "username": "eliodirupo"}, {"created_at": "2014-05-21T07:59:02", "id": 469024554418180096, "sentiment": 0.2333333333333333, "text": "'The PS wants to create 1,000 more teaching posts. We also want to further develop internships in business' @Soirmag", "username": "eliodirupo"}, {"created_at": "2014-05-21T07:59:18", "id": 469024620180684800, "sentiment": 0.0, "text": "The MR is fond of the N-VA. This ideological gathering reminds me of the Martens-Gol Government, with 3 index jumps' @Soirmag", "username": "eliodirupo"}, {"created_at": "2014-05-21T08:04:41", "id": 469025974957645824, "sentiment": 0.0, "text": "'The Secu, the preservation of indexing, the increase in minimum wages, it is the PS who made them, not the PTB' @Soirmag", "username": "eliodirupo"}, {"created_at": "2014-05-21T08:04:52", "id": 469026022709792768, "sentiment": 0.0, "text": "'Every voice that does not go to the PS opens the road to a government of rights' @Soirmag", "username": "eliodirupo"}, {"created_at": "2014-05-21T08:05:59", "id": 469026302906085376, "sentiment": 0.0, "text": "Find my interview with Rachid Madrane in @soirmag @PSofficiel #PlusFortsEnsemble http://t.co/GX9HGGXPVU", "username": "eliodirupo"}, {"created_at": "2014-05-21T08:29:51", "id": 469032309417852929, "sentiment": 0.0, "text": "RT @PSofficiel: @MR_officiel D. Reynders RTBF 25/04: There is still room for maneuver in terms of tax revenues for the climate, po ...", "username": "eliodirupo"}, {"created_at": "2014-05-21T08:32:44", "id": 469033034839523328, "sentiment": 0.6166666666666667, "text": "With @RobertJenrick - our great by-election candidate - at the Newark Advertiser. He'll be a strong voice for Newark. http://t.co/yNHESH0bEP", "username": "David_Cameron"}, {"created_at": "2014-05-21T08:35:15", "id": 469033669118926848, "sentiment": 0.2, "text": "The election of the next House of Representatives is an important step in the democratic process of the homeland. But there must be clarity about the duration of this board and when ... http://t.co/7FV5AghKPs", "username": "MustafaAG"}, {"created_at": "2014-05-21T08:51:10", "id": 469037674264035328, "sentiment": 0.8, "text": "RT @PSofficiel: Reynders Bxls for all p113: implement a motorway toll at Bxls entrances or an intelligent tax per km traveled ...", "username": "eliodirupo"}, {"created_at": "2014-05-21T09:21:31", "id": 469045311621840896, "sentiment": 0.15000000000000002, "text": "A RT: our concrete proposals for employment @PSofficiel #PlusFortsEnsemble http://t.co/e12NKmXdvQ http://t.co/ujtSnpBhYO", "username": "eliodirupo"}, {"created_at": "2014-05-21T09:29:06", "id": 469047220109836288, "sentiment": 0.3, "text": "On the streets of Newark with @RobertJenrick and Boris. Robert is fighting to secure a better future for Newark. http://t.co/ofZoNnr7q7", "username": "David_Cameron"}, {"created_at": "2014-05-21T09:55:18", "id": 469053812976934913, "sentiment": 0.15000000000000002, "text": "A RT: our concrete proposals for youth employment @PSofficiel #PlusFortsEnsemble http://t.co/ERjRGxWuBM", "username": "eliodirupo"}, {"created_at": "2014-05-21T10:22:53", "id": 469060754399039488, "sentiment": 0.15000000000000002, "text": "A RT: our concrete proposals for purchasing power (1) @PSofficiel #MoreFortsEnsemble http://t.co/e12NKmXdvQ http://t.co/gJ7iYp7bJE", "username": "eliodirupo"}, {"created_at": "2014-05-21T10:23:19", "id": 469060864243675136, "sentiment": 0.15000000000000002, "text": "A RT: our concrete proposals for purchasing power (2) @PSofficiel #MoreFortsEnsemble http://t.co/e12NKmXdvQ http://t.co/xWc41Kz4qy", "username": "eliodirupo"}, {"created_at": "2014-05-21T10:33:43", "id": 469063481455439873, "sentiment": 0.0, "text": "RT @PTVph: NOW ON PTV: State dinner in honor of Vietnamese Prime Minister Nguyen Tan Dung.", "username": "noynoyaquino"}, {"created_at": "2014-05-21T10:36:48", "id": 469064259024855040, "sentiment": 0.0, "text": "[Adm-02] Pres. Aquino welcomes the members of the ASEAN Business Club during their courtesy call in Malaca\u00f1ang. https://t.co/Tp0hG6oN3z", "username": "noynoyaquino"}, {"created_at": "2014-05-21T10:38:41", "id": 469064730280493056, "sentiment": 0.0, "text": "My letter to Pdt #Putin on #energy security & gas delivery to #Ukraine. Imperative that all sides continue to engage http://t.co/4jPhMj7Nrc", "username": "JMDBarroso"}, {"created_at": "2014-05-21T10:51:14", "id": 469067889585455104, "sentiment": 0.09166666666666667, "text": "A RT: our concrete proposals for a social revival @PSofficiel #PlusFortsEnsemble http://t.co/e12NKmXdvQ http://t.co/gaQQT3eRWK", "username": "eliodirupo"}, {"created_at": "2014-05-21T11:15:34", "id": 469074011989999616, "sentiment": 0.3, "text": "Een kat in het nauw rare maakt sprongen ...", "username": "eliodirupo"}, {"created_at": "2014-05-21T11:15:34", "id": 469074014997315584, "sentiment": 0.5, "text": "Today, the government is accountable for the policy pursued in 2013 #Reference day. To find out more, see: http://t.co/Vcsfdb7MSP", "username": "MinPres"}, {"created_at": "2014-05-21T11:15:52", "id": 469074089538510848, "sentiment": -0.2, "text": "#Reference day: after a heavy year, now a view of growth. Continue with recovery policy to adjust facilities & strengthen economy.", "username": "MinPres"}, {"created_at": "2014-05-21T11:32:47", "id": 469078345981100033, "sentiment": 0.15000000000000002, "text": "A RT: our concrete proposals for teaching @PSofficiel #PlusFortsEnsemble http://t.co/e12NKmXdvQ http://t.co/t8L3GXg6nY", "username": "eliodirupo"}, {"created_at": "2014-05-21T11:47:22", "id": 469082018509094912, "sentiment": 0.0, "text": "The talks within the visit will facilitate further development of relations between the two countries.", "username": "azpresident"}, {"created_at": "2014-05-21T11:47:34", "id": 469082067255312384, "sentiment": 0.775, "text": "We attach great importance to these relations and these relations are developing successfully.", "username": "azpresident"}, {"created_at": "2014-05-21T11:47:51", "id": 469082138009034753, "sentiment": 0.0, "text": "Today Azerbaijan declares its position in the world as an independent state.", "username": "azpresident"}, {"created_at": "2014-05-21T11:48:07", "id": 469082204987850753, "sentiment": -0.018333333333333333, "text": "The main reason for our support is that we always have an independent path, pursue an independent foreign policy, as well as an active regional policy.", "username": "azpresident"}, {"created_at": "2014-05-21T11:48:16", "id": 469082242879201280, "sentiment": 0.0, "text": "Our position is based on the principles of international law and justice.", "username": "azpresident"}, {"created_at": "2014-05-21T11:49:03", "id": 469082438191153152, "sentiment": 0.0, "text": "Looking at the history of Azerbaijan's development, once again you assure that national interests are above all (cont) http://t.co/1iGmUIMCTO", "username": "azpresident"}, {"created_at": "2014-05-21T11:49:16", "id": 469082495481171968, "sentiment": 0.0, "text": "We pursue our policy on the basis of national development and strengthening our independence.", "username": "azpresident"}, {"created_at": "2014-05-21T11:49:25", "id": 469082533682900992, "sentiment": 0.3, "text": "We have been the founder of our own destiny, we set our priorities and our future.", "username": "azpresident"}, {"created_at": "2014-05-21T11:49:40", "id": 469082596224143360, "sentiment": 0.22499999999999998, "text": "There can be no greater happiness in the world.", "username": "azpresident"}, {"created_at": "2014-05-21T11:50:19", "id": 469082758489206784, "sentiment": 0.2, "text": "There is tolerance and tolerance in Azerbaijan. Our people are very hospitable. Azerbaijan is a multinational country.", "username": "azpresident"}, {"created_at": "2014-05-21T11:50:47", "id": 469082874533007361, "sentiment": 0.0, "text": "There has never been any confusion, confrontation, or conflicts on national and religious grounds.", "username": "azpresident"}, {"created_at": "2014-05-21T11:51:35", "id": 469083078955003905, "sentiment": 0.1875, "text": "Armenians, as representatives of all other nations, lived in Azerbaijan, enjoying all the blessings.", "username": "azpresident"}, {"created_at": "2014-05-21T11:51:57", "id": 469083169442902016, "sentiment": -0.5, "text": "Unfortunately, the nationalist forces who came to power in Armenia started a war against our country.", "username": "azpresident"}, {"created_at": "2014-05-21T11:52:15", "id": 469083243598213120, "sentiment": -0.30000000000000004, "text": "As a result of this war, our territories were occupied, and our citizens were forced to leave their hometowns.", "username": "azpresident"}, {"created_at": "2014-05-21T11:52:30", "id": 469083307070586880, "sentiment": 0.0, "text": "The UN Security Council has requested four (cont) http://t.co/fpFCbN4PNc to demand the withdrawal of Armenian occupying forces from Azerbaijan", "username": "azpresident"}, {"created_at": "2014-05-21T11:52:57", "id": 469083420321001474, "sentiment": 0.05, "text": "No sanctions against Armenia, no international condemnation. This is the reason why the conflict has not been resolved so far.", "username": "azpresident"}, {"created_at": "2014-05-21T11:53:32", "id": 469083569428496384, "sentiment": 0.025, "text": "Azerbaijan will strengthen its economic, military and political potential. We want our native land - Karabakh, (cont) http://t.co/JjCvZThM87", "username": "azpresident"}, {"created_at": "2014-05-21T11:53:46", "id": 469083625489575937, "sentiment": 0.1, "text": "Projects implemented in Azerbaijan have completely changed the region's energy map.", "username": "azpresident"}, {"created_at": "2014-05-21T11:53:58", "id": 469083677054341121, "sentiment": 0.04166666666666667, "text": "For the first time, we have combined the Caspian region with the Black Sea and the Mediterranean region through oil and gas pipelines.", "username": "azpresident"}, {"created_at": "2014-05-21T11:54:04", "id": 469083703059046401, "sentiment": 0.5, "text": "This allows us and our neighbors to use more oil and gas resources more efficiently.", "username": "azpresident"}, {"created_at": "2014-05-21T11:59:33", "id": 469085081676824576, "sentiment": 0.10000000000000002, "text": "RT @Finance: Budget deficit and debt 2013 clearly presented in an infographic #Refund day http://t.co/iIASjOikI1", "username": "MinPres"}, {"created_at": "2014-05-21T12:00:55", "id": 469085427790782464, "sentiment": 0.15000000000000002, "text": "A RT: our concrete proposals for families @PSofficiel #PlusFortsEnsemble http://t.co/e12NKmXdvQ http://t.co/auJx6EFegZ", "username": "eliodirupo"}, {"created_at": "2014-05-21T12:24:28", "id": 469091353214091264, "sentiment": 0.13636363636363635, "text": "My press point with @PrimeMinisterGE #Garibashvili is about to start, watch live at http://t.co/pDE27ontue", "username": "JMDBarroso"}, {"created_at": "2014-05-21T12:35:51", "id": 469094215725510656, "sentiment": 0.0, "text": "We are committed to the policy of cooperation with the People's Republic of China in all directions.", "username": "azpresident"}, {"created_at": "2014-05-21T12:36:14", "id": 469094314794962944, "sentiment": 0.17500000000000002, "text": "We want to deepen this cooperation, and we are ready to take concrete steps in this direction.", "username": "azpresident"}, {"created_at": "2014-05-21T12:36:30", "id": 469094380913967104, "sentiment": 0.0, "text": "Azerbaijan has always supported China in the United Nations and will continue to support it.", "username": "azpresident"}, {"created_at": "2014-05-21T12:51:40", "id": 469098197340930048, "sentiment": 0.0, "text": "@EU_Commission stands by a democratic, prosperous & united #Georgia. Visit of @PrimeMinisterGE #Garibashvili", "username": "JMDBarroso"}, {"created_at": "2014-05-21T12:51:55", "id": 469098260918194176, "sentiment": 0.0, "text": "#EU is firmly committed to political association and economic integration with #Georgia. Visit of @PrimeMinisterGE #Garibashvili", "username": "JMDBarroso"}, {"created_at": "2014-05-21T12:52:57", "id": 469098521996820480, "sentiment": 0.0, "text": "The signature of #AssociationAgreement in about 1 month will be a landmark in #EU #Georgia relation. Visit of @PrimeMinisterGE #Garibashvili", "username": "JMDBarroso"}, {"created_at": "2014-05-21T12:54:02", "id": 469098792751759361, "sentiment": 0.4, "text": "Today @PrimeMinisterGE #Garibashvili and I signed a Financing Agreement worth \u20ac 19 million aiming at achieving better governance in #Georgia", "username": "JMDBarroso"}, {"created_at": "2014-05-21T12:54:16", "id": 469098853002924032, "sentiment": 0.15000000000000002, "text": "A RT: our concrete proposals to improve health care (1) @PSofficiel #MoreFortsEnsemble http://t.co/o5LjzcXtsD", "username": "eliodirupo"}, {"created_at": "2014-05-21T12:54:40", "id": 469098952797986816, "sentiment": 0.15000000000000002, "text": "A RT: our concrete proposals to improve healthcare (2) @PSofficiel #MoreFortsEnsemble http://t.co/u6hJIdW3Mp", "username": "eliodirupo"}, {"created_at": "2014-05-21T12:54:49", "id": 469098990286688256, "sentiment": 0.6333333333333334, "text": "#Ukraine: free and fair presidential elections on 25 May are of great importance for stability & we expect that everyone respects them.", "username": "JMDBarroso"}, {"created_at": "2014-05-21T13:07:45", "id": 469102244869443585, "sentiment": 0.35, "text": "Better councils, a stronger economy and real change in Europe - Boris and I taking our campaign message to Ealing. http://t.co/2m4uuIVmGE", "username": "David_Cameron"}, {"created_at": "2014-05-21T13:17:21", "id": 469104660595220480, "sentiment": 0.0, "text": "[Adm-02] P-Noy welcomes Prime Minister Nguyen Tan Dung at the Malaca\u00f1an Palace Grounds. http://t.co/bbprsACBx9", "username": "noynoyaquino"}, {"created_at": "2014-05-21T13:25:02", "id": 469106594660515840, "sentiment": 0.13636363636363635, "text": "Now at #ESSC conference closing ceremony with @GOettingerEU & @premiertusk watch live http://t.co/oeY0Lp481y", "username": "JMDBarroso"}, {"created_at": "2014-05-21T13:27:12", "id": 469107138862649344, "sentiment": 0.5, "text": "[Adm-02] Philippines, Vietnam agree on enhancing two-way trade in 2 years. Read more here: http://t.co/RA7upP2VHL", "username": "noynoyaquino"}, {"created_at": "2014-05-21T13:27:13", "id": 469107143736848384, "sentiment": 0.0, "text": "#Europe is facing a threat to peace, stability & security the likes of which we have not seen since fall of Iron Curtain. #Ukraine #ESSC", "username": "JMDBarroso"}, {"created_at": "2014-05-21T13:30:46", "id": 469108037371047937, "sentiment": 0.1, "text": "Increasing security of #energy supply is vital for our prosperity, for our strength and our credibility #EU #ESSC", "username": "JMDBarroso"}, {"created_at": "2014-05-21T13:33:06", "id": 469108623889924096, "sentiment": 0.2, "text": "#EU external #energy bill today represents more than \u20ac1 billion per day and more than a fifth of total European imports.", "username": "JMDBarroso"}, {"created_at": "2014-05-21T13:35:32", "id": 469109235906007040, "sentiment": 0.225, "text": "#Energy security is intrinsically linked to #EU becoming a competitive, low-carbon economy. #ESSC", "username": "JMDBarroso"}, {"created_at": "2014-05-21T13:42:17", "id": 469110934657835008, "sentiment": 0.15000000000000002, "text": "A RT: our concrete proposals for seniors @PSofficiel #PlusFortsEnsemble http://t.co/e12NKmXdvQ http://t.co/GuEW47Dhj8", "username": "eliodirupo"}, {"created_at": "2014-05-21T13:48:39", "id": 469112539625033728, "sentiment": 0.0, "text": "#EU remains world's largest #energy market. We have shared interest w/ intl partners in transparency, reliability & responsibility #ESSC", "username": "JMDBarroso"}, {"created_at": "2014-05-21T13:55:13", "id": 469114189152550912, "sentiment": 0.0, "text": "Participating this afternoon at the Energy Security Strategy Conference #ESSC w/ PM #Tusk @PremierRP & @GOettingerEU http://t.co/a5nxteHz2p", "username": "JMDBarroso"}, {"created_at": "2014-05-21T14:28:59", "id": 469122688037167104, "sentiment": 0.15000000000000002, "text": "A RT: our concrete proposals for housing @PSofficiel #MoreFortsEnsemble http://t.co/e12NKmXdvQ http://t.co/bL2kv2kcyj", "username": "eliodirupo"}, {"created_at": "2014-05-21T14:37:30", "id": 469124831028338690, "sentiment": 0.3375, "text": "V. happy w/ visit of #Georgian government today, seeing each other again in June. http://t.co/dBtJpiP1M8 http://t.co/v18ZBiHGUN", "username": "JMDBarroso"}, {"created_at": "2014-05-21T14:42:23", "id": 469126061054504960, "sentiment": 0.15000000000000002, "text": "A RT: our concrete proposals for mobility @PSofficiel #PlusFortsEnsemble http://t.co/e12NKmXdvQ http://t.co/0PBMut2pPL", "username": "eliodirupo"}, {"created_at": "2014-05-21T14:44:49", "id": 469126671459950593, "sentiment": 0.07500000000000001, "text": "A RT: our concrete proposals for public services @PSofficiel #PlusFortsEnsemble http://t.co/e12NKmXdvQ http://t.co/RFnf2Dslon", "username": "eliodirupo"}, {"created_at": "2014-05-21T15:25:15", "id": 469136847613206528, "sentiment": 0.0, "text": "Invitation letter to informal dinner Tuesday 27/5 on #EP2014 elections and #Ukraine #EUCO http://t.co/C1zaznBeoq", "username": "eucopresident"}, {"created_at": "2014-05-21T15:58:37", "id": 469145245117317122, "sentiment": 0.5, "text": "Today saw the distribution of the Arab Press Award .. With more than 4500 entries, the award has become an incentive for creativity and excellence in the media in our Arab world", "username": "HHShkMohd"}, {"created_at": "2014-05-21T15:59:11", "id": 469145388436713472, "sentiment": 0.2916666666666667, "text": "The media field is full of talented young and creative talents. I tell these young people the future for you and the field ahead of you.", "username": "HHShkMohd"}, {"created_at": "2014-05-21T16:14:10", "id": 469149157765443584, "sentiment": 0.7, "text": "Good evening! I will be tomorrow morning at 7:35 in @telematintv on @ France2tv @MarieMamgioglou", "username": "eliodirupo"}, {"created_at": "2014-05-21T16:30:24", "id": 469153243558596609, "sentiment": 0.2, "text": "Tomorrow's elections are your chance to get real change in Europe. Share this today - and vote Conservative tomorrow. http://t.co/cO78IwQIEZ", "username": "David_Cameron"}, {"created_at": "2014-05-21T16:31:17", "id": 469153467878346753, "sentiment": 0.5, "text": "It seems that there is more care and concern for the welfare of pets, than for the life and dignity of the children who are about to be born", "username": "sebastianpinera"}, {"created_at": "2014-05-21T16:47:12", "id": 469157473811972096, "sentiment": 0.15, "text": "@EU_Commission will make v. clear proposals on #energy to the European Council #EUCO in June, my full speech at #EESC http://t.co/n4YZGE7XTi", "username": "JMDBarroso"}, {"created_at": "2014-05-21T16:48:04", "id": 469157691471187968, "sentiment": 0.0, "text": "Meet the people of Dour - Huisbezoeken in Dour @PSofficiel #PlusFortsEnsemble http://t.co/4DoOyFZLA2", "username": "eliodirupo"}, {"created_at": "2014-05-21T17:32:32", "id": 469168880368492545, "sentiment": 0.0, "text": ". @ LaureenHarper and I are honored to join The Prince of Wales and Duchess of Cornwall in Manitoba today. #cdnpoli http://t.co/NJyYVyooUo", "username": "stephenharper"}, {"created_at": "2014-05-21T17:58:42", "id": 469175463626424321, "sentiment": 0.0, "text": "Watch my @Channel4News interview with @jonsnowC4 - coming up shortly. http://t.co/TF4xXOBYAj", "username": "David_Cameron"}, {"created_at": "2014-05-21T18:01:11", "id": 469176088728309760, "sentiment": 0.3166666666666667, "text": "Congratulations to Maldives national football team for winning tonight's match against Kyrgyzstan and for playing a beautiful game.", "username": "DrWaheedH"}, {"created_at": "2014-05-21T18:01:28", "id": 469176161575378945, "sentiment": 0.0, "text": "It is legitimate to try to save the life of the mother, even when, as an unwanted result, the life of the unborn child is put at risk", "username": "sebastianpinera"}, {"created_at": "2014-05-21T18:05:52", "id": 469177269077180416, "sentiment": 0.047272727272727265, "text": "That is therapy and not abortion, because the objective is to save mother life and not destroy the life of a new being, essentially innocent and vulnerable", "username": "sebastianpinera"}, {"created_at": "2014-05-21T18:07:10", "id": 469177597432430592, "sentiment": 0.0, "text": "Flying paper airplanes w / @LaureenHarper, Prince of Wales & Duchess of Cornwall in Winnipeg. @ClarenceHouse http://t.co/6waQNjYtNo", "username": "stephenharper"}, {"created_at": "2014-05-21T18:08:31", "id": 469177936885862401, "sentiment": -0.14285714285714285, "text": "We must protect the life and dignity of all unborn children. We have no right to decide who lives and who dies.", "username": "sebastianpinera"}, {"created_at": "2014-05-21T18:35:01", "id": 469184603740450816, "sentiment": 0.290625, "text": "RT @RCGS_SGRC: HUGE thanks to @pmharper for this major gift to @RCGS_SGRC, which will help make Canada better known to Canadians! http: //t....", "username": "stephenharper"}, {"created_at": "2014-05-21T18:53:33", "id": 469189268171399168, "sentiment": 0.0, "text": "Today marks two years of the #Government 's \u0441urrent Cabinet http://t.co/nvOW1waL8u", "username": "MedvedevRussiaE"}, {"created_at": "2014-05-21T19:18:22", "id": 469195514626707457, "sentiment": 1.0, "text": "RT @RCGS_SGRC: We're so honored to receive a gift on behalf of @ClarenceHouse! A wonderful legacy of a wonderful visit! http://t.co/Y93u2q...", "username": "stephenharper"}, {"created_at": "2014-05-21T19:36:58", "id": 469200196103315458, "sentiment": 0.0, "text": "Address by Prime Minister Antonis Samaras at the central event for the 73rd Anniversary of the Historical Battle of Cretehttp: //t.co/o5JdXOgJz2", "username": "PrimeministerGR"}]